cjvalpy-0.4.1.dist-info/METADATA
cjvalpy-0.4.1.dist-info/WHEEL
cjvalpy/__init__.py
cjvalpy/cjvalpy.cpython-311-darwin.so
cjvalpy-0.4.1.dist-info/RECORD
