Metadata-Version: 2.1
Name: cjvalpy
Version: 0.4.1
Summary: The Python bindings of the official CityJSON validator
Home-Page: https://github.com/hugoledoux/cjvalpy
Author: Hugo Ledoux <h.ledoux@tudelft.nl>
Author-email: Hugo Ledoux <h.ledoux@tudelft.nl>
License: MIT
Project-URL: Source Code, https://github.com/hugoledoux/cjvalpy
